MANIFEST.in
setup.py
ftwo/__init__.py
ftwo/attrcache.py
ftwo/extract.py
ftwo/heartbeat.py
ftwo.egg-info/PKG-INFO
ftwo.egg-info/SOURCES.txt
ftwo.egg-info/dependency_links.txt
ftwo.egg-info/not-zip-safe
ftwo.egg-info/top_level.txt