Metadata-Version: 1.0
Name: ftwo
Version: 0.1.2
Summary: Some common use functions
Home-page: https://bitbucket.org/lerry/42
Author: Lerry
Author-email: lvdachao@gmail.com
License: UNKNOWN
Platform: UNKNOWN
